ckanext_heroku-0.5.1-py2.7-nspkg.pth
ckanext/heroku/__init__.py
ckanext/heroku/plugin.py
ckanext/heroku/tests/__init__.py
ckanext/heroku/tests/test_plugin.py
ckanext_heroku-0.5.1.dist-info/METADATA
ckanext_heroku-0.5.1.dist-info/RECORD
ckanext_heroku-0.5.1.dist-info/WHEEL
ckanext_heroku-0.5.1.dist-info/entry_points.txt
ckanext_heroku-0.5.1.dist-info/namespace_packages.txt
ckanext_heroku-0.5.1.dist-info/top_level.txt
