Metadata-Version: 2.1
Name: ckanext-heroku
Version: 0.5.1
Summary: Sets proper config options when running CKAN on Heroku
Home-page: https://github.com/nerevu/ckanext-heroku
Author: Reuben Cummings
Author-email: rcummings@nerevu.com
License: MIT
Keywords: CKAN heroku
Platform: UNKNOWN
Classifier: Development Status :: 4 - Beta
Classifier: License :: OSI Approved :: GNU Affero General Public License v3 or later (AGPLv3+)
Classifier: Programming Language :: Python :: 2.7
